[
    {
        "name": "GOBLIN",
        "tags": ["ENEMY_MELEE"],
        "statsByFloorTier": {
            "1": { "health": 28,  "energy": 8  },
            "2": { "health": 48,  "energy": 12 },
            "3": { "health": 72,  "energy": 18 },
            "4": { "health": 105, "energy": 25 }
        },
        "gambits": [
            {
                "id": "goblin_rush",
                "priority": 1,
                "conditions": {
                    "operator": "AND",
                    "conditions": []
                },
                "targetSelector": {
                    "context": { "targetType": "ENEMY", "filters": [] },
                    "sort": "LOWEST_HP"
                },
                "intent": {
                    "kind": "ACTION",
                    "actionId": "attack_basic"
                }
            },
            {
                "id": "goblin_approach",
                "priority": 2,
                "conditions": {
                    "operator": "AND",
                    "conditions": []
                },
                "targetSelector": {
                    "context": { "targetType": "ENEMY", "filters": [] },
                    "sort": "NEAREST"
                },
                "intent": {
                    "kind": "MOVEMENT",
                    "strategy": "APPROACH"
                }
            }
        ]
    },
    {
        "name": "KNIGHT",
        "tags": ["ENEMY_MELEE", "ENEMY_TANK"],
        "statsByFloorTier": {
            "1": { "health": 65,  "energy": 10 },
            "2": { "health": 110, "energy": 15 },
            "3": { "health": 165, "energy": 22 },
            "4": { "health": 240, "energy": 30 }
        },
        "gambits": [
            {
                "id": "knight_strike",
                "priority": 1,
                "conditions": {
                    "operator": "AND",
                    "conditions": []
                },
                "targetSelector": {
                    "context": { "targetType": "ENEMY", "filters": [] },
                    "sort": "LOWEST_HP"
                },
                "intent": {
                    "kind": "ACTION",
                    "actionId": "attack_basic"
                }
            },
            {
                "id": "knight_advance",
                "priority": 2,
                "conditions": {
                    "operator": "AND",
                    "conditions": []
                },
                "targetSelector": {
                    "context": { "targetType": "ENEMY", "filters": [] },
                    "sort": "NEAREST"
                },
                "intent": {
                    "kind": "MOVEMENT",
                    "strategy": "APPROACH"
                }
            }
        ]
    },
    {
        "name": "ALIEN",
        "tags": ["ENEMY_RANGED"],
        "statsByFloorTier": {
            "1": { "health": 22,  "energy": 22 },
            "2": { "health": 38,  "energy": 35 },
            "3": { "health": 58,  "energy": 52 },
            "4": { "health": 85,  "energy": 75 }
        },
        "gambits": [
            {
                "id": "alien_shoot",
                "priority": 1,
                "conditions": {
                    "operator": "AND",
                    "conditions": []
                },
                "targetSelector": {
                    "context": { "targetType": "ENEMY", "filters": [] },
                    "sort": "HIGHEST_HP"
                },
                "intent": {
                    "kind": "ACTION",
                    "actionId": "attack_basic"
                }
            },
            {
                "id": "alien_keep_distance",
                "priority": 2,
                "conditions": {
                    "operator": "AND",
                    "conditions": []
                },
                "targetSelector": {
                    "context": { "targetType": "ENEMY", "filters": [] },
                    "sort": "NEAREST"
                },
                "intent": {
                    "kind": "MOVEMENT",
                    "strategy": "FLEE"
                }
            }
        ]
    }
]